[
  {
    "id": "javascript",
    "name": "JavaScript",
    "iconType": "potion",
    "type": "Language",
    "rarity": "LEGENDARY",
    "stats": "INT +95, SPD +80",
    "description": "Primary engine for building dynamic client-side experiences, custom HTML elements, and asynchronous agent pipelines."
  },
  {
    "id": "css",
    "name": "CSS",
    "iconType": "shield",
    "type": "Styling",
    "rarity": "RARE",
    "stats": "DEF +90, RES +95",
    "description": "Essential tool used to style layout grids, implement CRT screen scanlines, and handle neon-glow micro-animations."
  },
  {
    "id": "blender",
    "name": "Blender",
    "iconType": "sword",
    "type": "3D Modeling",
    "rarity": "EPIC",
    "stats": "STR +88, DEX +50",
    "description": "Creative suite for sculpting low-poly meshes, texture painting, and exporting optimized GLB/GLTF assets."
  }
]
